dslclib/__init__.py
dslclib/src/__init__.py
dslclib/src/base.py
dslclib/src/body_controller.py
dslclib/src/expression_controller.py
dslclib/src/face_recognition.py
dslclib/src/speech_recognition.py
dslclib/src/tts.py
dslclib-0.3.0.dist-info/METADATA
dslclib-0.3.0.dist-info/WHEEL
dslclib-0.3.0.dist-info/RECORD
