Metadata-Version: 2.1
Name: dslclib
Version: 0.3.0
Summary: 対話システムライブコンペティションに使用できるPythonライブラリ
Author: Yuta SASAKI
Author-email: yubo1336@lr.pi.titech.ac.jp
Requires-Python: >=3.10
Classifier: Programming Language :: Python :: 3
Classifier: Programming Language :: Python :: 3.10
Classifier: Programming Language :: Python :: 3.11
Requires-Dist: furo (>=2023.5.20,<2024.0.0)
Requires-Dist: sphinx (>=7.0.1,<8.0.0)
